dadaia_tools/__init__.py
dadaia_tools/azure_key_vault_client.py
dadaia_tools/azure_storage_blob_admin.py
dadaia_tools/azure_storage_blob_client.py
dadaia_tools/azure_storage_queue_client.py
dadaia_tools/azure_storage_table_client.py
dadaia_tools/etherscan_client.py
dadaia_tools/kafka_admin.py
dadaia_tools/kafka_client.py
dadaia_tools/redis_client.py
dadaia_tools/singleton.py
dadaia_tools-0.1.2.dist-info/METADATA
dadaia_tools-0.1.2.dist-info/WHEEL
dadaia_tools-0.1.2.dist-info/RECORD
