Metadata-Version: 2.1
Name: dadaia-tools
Version: 0.1.2
Summary: 
Author: Your Name
Author-email: you@example.com
Requires-Python: >=3.8,<4.0
Classifier: Programming Language :: Python :: 3
Classifier: Programming Language :: Python :: 3.8
Classifier: Programming Language :: Python :: 3.9
Classifier: Programming Language :: Python :: 3.10
Classifier: Programming Language :: Python :: 3.11
Requires-Dist: azure-data-tables (>=12.4.4,<13.0.0)
Requires-Dist: azure-identity (>=1.14.0,<2.0.0)
Requires-Dist: azure-keyvault-secrets (>=4.7.0,<5.0.0)
Requires-Dist: azure-storage-blob (>=12.18.2,<13.0.0)
Requires-Dist: azure-storage-queue (>=12.7.2,<13.0.0)
Requires-Dist: boto3 (>=1.28.57,<2.0.0)
Requires-Dist: kafka-python (>=2.0.2,<3.0.0)
Requires-Dist: redis (>=5.0.0,<6.0.0)
